Workbook

Sheet My Inflation
A1: YOUR REAL INFLATION CALCULATOR | H1: Fill 'what you paid before' to get YOUR real rate. Can't remember? Leave it blank and the sheet uses the standard rate instead.
A2: Don't trust the average — measure your own. Type what you ACTUALLY pay now vs a few years back, and the sheet works out your real inflation. | H2: Compare the SAME thing — same school, same size grocery basket, same policy — so we measure price rises, not lifestyle upgrades.
A4: HOW TO USE — Fill the YELLOW cells: what you pay now, what you paid before, and how many years ago. Everything else fills itself.
A6: Category | B6: What you pay now (₹/mo) | C6: What you paid before (₹/mo) | D6: Years ago | E6: Your real yearly rise | F6: Standard rate (if unsure) | G6: Rate used
A7: Food & groceries | B7: 11500 | C7: 7000 | D7: 5 | E7: =IF(AND(C7>0,D7>0),(B7/C7)^(1/D7)-1,"") -> 0.10438363 | F7: 0.04 | G7: =IF(AND(C7>0,D7>0),(B7/C7)^(1/D7)-1,F7) -> 0.10438363
A8: Rent | B8: 25000 | C8: 18000 | D8: 3 | E8: =IF(AND(C8>0,D8>0),(B8/C8)^(1/D8)-1,"") -> 0.11572158 | F8: 0.05 | G8: =IF(AND(C8>0,D8>0),(B8/C8)^(1/D8)-1,F8) -> 0.11572158
A9: Home loan EMI (fixed — does NOT inflate) | B9: 0 | E9: =IF(AND(C9>0,D9>0),(B9/C9)^(1/D9)-1,"") | F9: 0 | G9: =IF(AND(C9>0,D9>0),(B9/C9)^(1/D9)-1,F9) -> 0
A10: Kids' school / college fees | B10: 30000 | C10: 23000 | D10: 3 | E10: =IF(AND(C10>0,D10>0),(B10/C10)^(1/D10)-1,"") -> 0.092608244 | F10: 0.1 | G10: =IF(AND(C10>0,D10>0),(B10/C10)^(1/D10)-1,F10) -> 0.092608244
A11: Medical + health insurance | B11: 9000 | C11: 4700 | D11: 3 | E11: =IF(AND(C11>0,D11>0),(B11/C11)^(1/D11)-1,"") -> 0.24179017 | F11: 0.14 | G11: =IF(AND(C11>0,D11>0),(B11/C11)^(1/D11)-1,F11) -> 0.24179017
A12: Lifestyle — eating out, OTT, travel, gadgets | B12: 13000 | C12: 10000 | D12: 4 | E12: =IF(AND(C12>0,D12>0),(B12/C12)^(1/D12)-1,"") -> 0.067789972 | F12: 0.05 | G12: =IF(AND(C12>0,D12>0),(B12/C12)^(1/D12)-1,F12) -> 0.067789972
A13: TOTAL you spend every month | B13: =SUM(B7:B12) -> 88500
A15: YOUR NUMBER
A16: Your personal inflation | B16: =IFERROR(SUMPRODUCT(B7:B12,G7:G12)/SUM(B7:B12),0) -> 0.11219299
A17: Generally considered number | B17: 0.06
A18: Your prices climb faster by | B18: =B16-B17 -> 0.052192992
A21: IS YOUR INVESTING KEEPING UP?
A22: What you invest every month now (SIP) | B22: 20000
A23: How much you raise it each year (your step-up) | B23: 0.1
A24: Step-up you need just to match your own inflation | B24: =B16 -> 0.11219299
A25: So raise your SIP next year by at least | B25: =B22*B16 -> 2243.8598
A26: =IF(B23<B16-0.001,"Your step-up is slower than your costs rise — your investing is quietly falling behind your own life.","Your step-up keeps pace with your inflation — that is the idea.") -> Your step-up is slower than your costs rise — your investing is quietly falling behind your own life.
A27: This only checks that your SIP grows as fast as your costs. It assumes NO investment return and promises none — for that, talk to a registered financial advisor.
A29: WHERE THE STANDARD RATES COME FROM
A30: • Food, Rent, Lifestyle — MoSPI Consumer Price Index (CPI). Real rent renewals often run higher than the CPI housing figure.
A31: • Home loan EMI — fixed by your loan; it does not inflate and gets lighter in real terms each year.
A32: • Kids' education — real school-fee inflation ~10–12% (1 Finance). Official CPI education (~3%) is dragged down by government-school fees.
A33: • Medical + insurance — ~14% from insurer & actuarial claims reports (ACKO India Health Report, Mercer Marsh).
A34: • Official comparison set to 6% — near the top of the RBI's comfort band. These are only used if you leave 'what you paid before' blank.
A36: Illustrative only. Shows how prices in YOUR basket may move.

Sheet Year by Year
A1: YEAR-BY-YEAR: HOW YOUR COSTS CLIMB
A2: Each expense grows at its own speed — watch school fees and medical pull away from the rest. 5-year marks are highlighted. Numbers flow from the main tab.
A4: Year | B4: Food | C4: Rent | D4: Home EMI | E4: School / college | F4: Medical | G4: Lifestyle | H4: TOTAL (your rate) | I4: If it were 6%
A5: 0 | B5: ='My Inflation'!$B$7*(1+'My Inflation'!$G$7)^$A5 -> 11500 | C5: ='My Inflation'!$B$8*(1+'My Inflation'!$G$8)^$A5 -> 25000 | D5: ='My Inflation'!$B$9*(1+'My Inflation'!$G$9)^$A5 -> 0 | E5: ='My Inflation'!$B$10*(1+'My Inflation'!$G$10)^$A5 -> 30000 | F5: ='My Inflation'!$B$11*(1+'My Inflation'!$G$11)^$A5 -> 9000 | G5: ='My Inflation'!$B$12*(1+'My Inflation'!$G$12)^$A5 -> 13000 | H5: =SUM(B5:G5) -> 88500 | I5: ='My Inflation'!$B$13*(1+'My Inflation'!$B$17)^$A5 -> 88500
A6: 1 | B6: ='My Inflation'!$B$7*(1+'My Inflation'!$G$7)^$A6 -> 12700.412 | C6: ='My Inflation'!$B$8*(1+'My Inflation'!$G$8)^$A6 -> 27893.04 | D6: ='My Inflation'!$B$9*(1+'My Inflation'!$G$9)^$A6 -> 0 | E6: ='My Inflation'!$B$10*(1+'My Inflation'!$G$10)^$A6 -> 32778.247 | F6: ='My Inflation'!$B$11*(1+'My Inflation'!$G$11)^$A6 -> 11176.112 | G6: ='My Inflation'!$B$12*(1+'My Inflation'!$G$12)^$A6 -> 13881.27 | H6: =SUM(B6:G6) -> 98429.08 | I6: ='My Inflation'!$B$13*(1+'My Inflation'!$B$17)^$A6 -> 93810
A7: 2 | B7: ='My Inflation'!$B$7*(1+'My Inflation'!$G$7)^$A7 -> 14026.127 | C7: ='My Inflation'!$B$8*(1+'My Inflation'!$G$8)^$A7 -> 31120.866 | D7: ='My Inflation'!$B$9*(1+'My Inflation'!$G$9)^$A7 -> 0 | E7: ='My Inflation'!$B$10*(1+'My Inflation'!$G$10)^$A7 -> 35813.783 | F7: ='My Inflation'!$B$11*(1+'My Inflation'!$G$11)^$A7 -> 13878.385 | G7: ='My Inflation'!$B$12*(1+'My Inflation'!$G$12)^$A7 -> 14822.281 | H7: =SUM(B7:G7) -> 109661.44 | I7: ='My Inflation'!$B$13*(1+'My Inflation'!$B$17)^$A7 -> 99438.6
A8: 3 | B8: ='My Inflation'!$B$7*(1+'My Inflation'!$G$7)^$A8 -> 15490.225 | C8: ='My Inflation'!$B$8*(1+'My Inflation'!$G$8)^$A8 -> 34722.222 | D8: ='My Inflation'!$B$9*(1+'My Inflation'!$G$9)^$A8 -> 0 | E8: ='My Inflation'!$B$10*(1+'My Inflation'!$G$10)^$A8 -> 39130.435 | F8: ='My Inflation'!$B$11*(1+'My Inflation'!$G$11)^$A8 -> 17234.043 | G8: ='My Inflation'!$B$12*(1+'My Inflation'!$G$12)^$A8 -> 15827.083 | H8: =SUM(B8:G8) -> 122404.01 | I8: ='My Inflation'!$B$13*(1+'My Inflation'!$B$17)^$A8 -> 105404.92
A9: 4 | B9: ='My Inflation'!$B$7*(1+'My Inflation'!$G$7)^$A9 -> 17107.151 | C9: ='My Inflation'!$B$8*(1+'My Inflation'!$G$8)^$A9 -> 38740.333 | D9: ='My Inflation'!$B$9*(1+'My Inflation'!$G$9)^$A9 -> 0 | E9: ='My Inflation'!$B$10*(1+'My Inflation'!$G$10)^$A9 -> 42754.236 | F9: ='My Inflation'!$B$11*(1+'My Inflation'!$G$11)^$A9 -> 21401.065 | G9: ='My Inflation'!$B$12*(1+'My Inflation'!$G$12)^$A9 -> 16900 | H9: =SUM(B9:G9) -> 136902.78 | I9: ='My Inflation'!$B$13*(1+'My Inflation'!$B$17)^$A9 -> 111729.21
A10: 5 | B10: ='My Inflation'!$B$7*(1+'My Inflation'!$G$7)^$A10 -> 18892.857 | C10: ='My Inflation'!$B$8*(1+'My Inflation'!$G$8)^$A10 -> 43223.425 | D10: ='My Inflation'!$B$9*(1+'My Inflation'!$G$9)^$A10 -> 0 | E10: ='My Inflation'!$B$10*(1+'My Inflation'!$G$10)^$A10 -> 46713.63 | F10: ='My Inflation'!$B$11*(1+'My Inflation'!$G$11)^$A10 -> 26575.632 | G10: ='My Inflation'!$B$12*(1+'My Inflation'!$G$12)^$A10 -> 18045.651 | H10: =SUM(B10:G10) -> 153451.2 | I10: ='My Inflation'!$B$13*(1+'My Inflation'!$B$17)^$A10 -> 118432.96
A11: 6 | B11: ='My Inflation'!$B$7*(1+'My Inflation'!$G$7)^$A11 -> 20864.962 | C11: ='My Inflation'!$B$8*(1+'My Inflation'!$G$8)^$A11 -> 48225.309 | D11: ='My Inflation'!$B$9*(1+'My Inflation'!$G$9)^$A11 -> 0 | E11: ='My Inflation'!$B$10*(1+'My Inflation'!$G$10)^$A11 -> 51039.698 | F11: ='My Inflation'!$B$11*(1+'My Inflation'!$G$11)^$A11 -> 33001.358 | G11: ='My Inflation'!$B$12*(1+'My Inflation'!$G$12)^$A11 -> 19268.965 | H11: =SUM(B11:G11) -> 172400.29 | I11: ='My Inflation'!$B$13*(1+'My Inflation'!$B$17)^$A11 -> 125538.94
A12: 7 | B12: ='My Inflation'!$B$7*(1+'My Inflation'!$G$7)^$A12 -> 23042.923 | C12: ='My Inflation'!$B$8*(1+'My Inflation'!$G$8)^$A12 -> 53806.018 | D12: ='My Inflation'!$B$9*(1+'My Inflation'!$G$9)^$A12 -> 0 | E12: ='My Inflation'!$B$10*(1+'My Inflation'!$G$10)^$A12 -> 55766.394 | F12: ='My Inflation'!$B$11*(1+'My Inflation'!$G$11)^$A12 -> 40980.762 | G12: ='My Inflation'!$B$12*(1+'My Inflation'!$G$12)^$A12 -> 20575.207 | H12: =SUM(B12:G12) -> 194171.3 | I12: ='My Inflation'!$B$13*(1+'My Inflation'!$B$17)^$A12 -> 133071.28
A13: 8 | B13: ='My Inflation'!$B$7*(1+'My Inflation'!$G$7)^$A13 -> 25448.226 | C13: ='My Inflation'!$B$8*(1+'My Inflation'!$G$8)^$A13 -> 60032.535 | D13: ='My Inflation'!$B$9*(1+'My Inflation'!$G$9)^$A13 -> 0 | E13: ='My Inflation'!$B$10*(1+'My Inflation'!$G$10)^$A13 -> 60930.822 | F13: ='My Inflation'!$B$11*(1+'My Inflation'!$G$11)^$A13 -> 50889.507 | G13: ='My Inflation'!$B$12*(1+'My Inflation'!$G$12)^$A13 -> 21970 | H13: =SUM(B13:G13) -> 219271.09 | I13: ='My Inflation'!$B$13*(1+'My Inflation'!$B$17)^$A13 -> 141055.55
A14: 9 | B14: ='My Inflation'!$B$7*(1+'My Inflation'!$G$7)^$A14 -> 28104.605 | C14: ='My Inflation'!$B$8*(1+'My Inflation'!$G$8)^$A14 -> 66979.595 | D14: ='My Inflation'!$B$9*(1+'My Inflation'!$G$9)^$A14 -> 0 | E14: ='My Inflation'!$B$10*(1+'My Inflation'!$G$10)^$A14 -> 66573.519 | F14: ='My Inflation'!$B$11*(1+'My Inflation'!$G$11)^$A14 -> 63194.09 | G14: ='My Inflation'!$B$12*(1+'My Inflation'!$G$12)^$A14 -> 23459.346 | H14: =SUM(B14:G14) -> 248311.15 | I14: ='My Inflation'!$B$13*(1+'My Inflation'!$B$17)^$A14 -> 149518.89
A15: 10 | B15: ='My Inflation'!$B$7*(1+'My Inflation'!$G$7)^$A15 -> 31038.265 | C15: ='My Inflation'!$B$8*(1+'My Inflation'!$G$8)^$A15 -> 74730.58 | D15: ='My Inflation'!$B$9*(1+'My Inflation'!$G$9)^$A15 -> 0 | E15: ='My Inflation'!$B$10*(1+'My Inflation'!$G$10)^$A15 -> 72738.775 | F15: ='My Inflation'!$B$11*(1+'My Inflation'!$G$11)^$A15 -> 78473.8 | G15: ='My Inflation'!$B$12*(1+'My Inflation'!$G$12)^$A15 -> 25049.654 | H15: =SUM(B15:G15) -> 282031.07 | I15: ='My Inflation'!$B$13*(1+'My Inflation'!$B$17)^$A15 -> 158490.02
A16: 11 | B16: ='My Inflation'!$B$7*(1+'My Inflation'!$G$7)^$A16 -> 34278.152 | C16: ='My Inflation'!$B$8*(1+'My Inflation'!$G$8)^$A16 -> 83378.521 | D16: ='My Inflation'!$B$9*(1+'My Inflation'!$G$9)^$A16 -> 0 | E16: ='My Inflation'!$B$10*(1+'My Inflation'!$G$10)^$A16 -> 79474.985 | F16: ='My Inflation'!$B$11*(1+'My Inflation'!$G$11)^$A16 -> 97447.993 | G16: ='My Inflation'!$B$12*(1+'My Inflation'!$G$12)^$A16 -> 26747.769 | H16: =SUM(B16:G16) -> 321327.42 | I16: ='My Inflation'!$B$13*(1+'My Inflation'!$B$17)^$A16 -> 167999.42
... A35: 30 | B35: ='My Inflation'!$B$7*(1+'My Inflation'!$G$7)^$A35 -> 226097.96 | C35: ='My Inflation'!$B$8*(1+'My Inflation'!$G$8)^$A35 -> 667751.76 | D35: ='My Inflation'!$B$9*(1+'My Inflation'!$G$9)^$A35 -> 0 | E35: ='My Inflation'!$B$10*(1+'My Inflation'!$G$10)^$A35 -> 427617.47 | F35: ='My Inflation'!$B$11*(1+'My Inflation'!$G$11)^$A35 -> 5966079.3 | G35: ='My Inflation'!$B$12*(1+'My Inflation'!$G$12)^$A35 -> 93007.612 | H35: =SUM(B35:G35) -> 7380554.1 | I35: ='My Inflation'!$B$13*(1+'My Inflation'!$B$17)^$A35 -> 508298.97
A37: 'TOTAL (your rate)' is what your current lifestyle costs that year. 'If it were 6%' is what the official number predicts — the gap is what nobody warned you about.

Sheet Goal
A1: ONE BIG GOAL — THE REAL PRICE TAG
A2: Plan a goal (a child's college, a wedding) against its REAL inflation, not the 6% everyone assumes. Fill the yellow cells.
A4: WHAT YOU'RE PLANNING FOR
A5: Goal (e.g. kid's college) | B5: Kid's college education
A6: What it costs TODAY | B6: 2000000
A7: Years until you need it | B7: 10
A8: Education inflation you expect | B8: 0.1
A9: What most people wrongly plan with | B9: 0.06
A11: WHAT IT ACTUALLY COSTS
A12: What you'd aim for at 6% | B12: =B6*(1+B9)^B7 -> 3581695.4
A13: What it will REALLY cost | B13: =B6*(1+B8)^B7 -> 5187484.9
A14: The shortfall you never saw coming | B14: =B13-B12 -> 1605789.5
A15: =IF(B13>0,"Plan for the red number, not the calm one. Aiming at "&TEXT(B12,"₹##,##,##0")&" leaves you short by "&TEXT(B13-B12,"₹##,##,##0")&" when the bill actually arrives.","Fill in your goal above.") -> Plan for the red number, not the calm one. Aiming at ₹3,581,695 leaves you short by ₹1,605,790 when the bill actually arrives.
A17: Illustrative only — not financial advice and no return is promised. For your own goals, consult a registered financial advisor.
