Workbook

Sheet How To Use
B3: DATA SOURCES USED:
B4: • NSO 2025 Health Survey — childbirth expenses (PIB/MOSPI)
B5: • CMS Education Survey 2025 (NSS 80th Round) — school expenditure data
B6: • NFHS-5 — fertility rate data
B7: • OECD — global fertility and affordability data
B8: • UNFPA 2025 India Report — reproductive choice data
B9: • PLFS — women's labour force participation data
B10: • Indian Academy of Pediatrics (IAP) — vaccination schedule & costs
B11: • Market research — daycare, nanny, diaper, baby product costs (2025-26)
B13: DISCLAIMER:
B14: This calculator is for educational purposes only. It is NOT financial advice.
B15: Actual costs will vary by city, lifestyle, choices, and timing. Use this as a starting point.

Sheet Your Profile
B2: YOUR FAMILY PROFILE
B3: Fill in the yellow cells below. These feed into all other sheets.
B5: BASIC DETAILS
B6: City Type | C6: Tier 2
C7: Type: Tier 1 or Tier 2
B8: Your Monthly Household Income (₹) | C8: 100000
B9: Partner's Monthly Income (₹) — 0 if single income | C9: 80000
B10: Current Monthly Rent / EMI (₹) | C10: 25000
B11: Annual Household Income (₹) | C11: =(C8+C9)*12 -> 2160000
B13: CHILD PLANNING PREFERENCES
B14: Hospital Type | C14: Private
C15: Type: Public or Private
B16: School Type | C16: Private Mid-Range
C17: Options: Government / Private Mid-Range / Private Premium
B18: Will both parents continue working? | C18: No
C19: Yes or No
B20: Childcare support (first 3 years) | C20: Daycare + Nanny
C21: Options: Grandparents / Daycare + Nanny / Daycare Only / Nanny Only
B22: Will you need to upgrade housing? (1BHK → 2BHK) | C22: Yes
B23: Will coaching/tuition be needed? | C23: Yes
B25: INFLATION ASSUMPTIONS
B26: General Inflation Rate | C26: 0.06
B27: Education Inflation Rate | C27: 0.1
B28: Healthcare Inflation Rate | C28: 0.08
B29: Source: Education inflation in India runs 8-12% historically. General CPI ~5-6%.

Sheet Birth Cost
B2: BIRTH & PREGNANCY COST
B3: Source: NSO 2025 Health Survey — Avg OOP childbirth: ₹2,299 (public) / ₹37,630 (private) / ₹14,775 (all)
B5: Expense Item | C5: Your Estimate (₹) | D5: Typical Range (₹) | E5: Notes
B6: PRE-PREGNANCY
B7: Fertility tests / pre-conception checkups | C7: 5000 | D7: 3,000 – 15,000 | E7: Optional but common in metro cities
B8: Prenatal vitamins & supplements (9 months) | C8: 9000 | D8: 5,000 – 15,000 | E8: Folic acid, iron, calcium, DHA
B10: PREGNANCY (9 MONTHS)
B11: OB-GYN consultation visits (10-12 visits) | C11: 15000 | D11: 5,000 – 30,000 | E11: ₹500-2,500 per visit private
B12: Ultrasound scans (3-5 scans) | C12: 8000 | D12: 3,000 – 15,000 | E12: NT scan, anomaly scan, growth scans
B13: Blood tests & lab work | C13: 8000 | D13: 4,000 – 15,000 | E13: CBC, thyroid, glucose, infections
B14: Medicines during pregnancy | C14: 5000 | D14: 2,000 – 10,000 | E14: Supplements + any prescribed meds
B15: Maternity clothing | C15: 8000 | D15: 3,000 – 15,000 | E15: Comfortable wear for 6+ months
B16: Prenatal classes (optional) | C16: 5000 | D16: 0 – 10,000 | E16: Lamaze, birthing workshops
B17: Mother's nutrition — extra food cost (9 months) | C17: 27000 | D17: 15,000 – 40,000 | E17: ~₹3,000/month extra nutrition
B18: Travel to hospital / clinic | C18: 5000 | D18: 2,000 – 10,000 | E18: Cab rides for checkups
B19: Sum
B20: DELIVERY & HOSPITAL
B21: Normal delivery — hospital charges | C21: 60000 | D21: 2,299 – 80,000 | E21: NSO avg: ₹2,299 public / ₹37,630 private
B22: C-section delivery (if needed) | C22: 80000 | D22: 20,000 – 2,00,000 | E22: Emergency C-section adds significant cost
B23: Hospital room charges (2-4 days) | C23: 30000 | D23: 0 – 50,000 | E23: Semi-private to private room
B24: Anesthesia & OT charges | C24: 10000 | D24: 5,000 – 25,000 | E24: Included in some packages
B25: Newborn screening tests | C25: 4500 | D25: 1,500 – 8,000 | E25: Hearing, metabolic screening
B27: POST-DELIVERY
B28: Mother's recovery & postpartum care | C28: 10000 | D28: 5,000 – 20,000 | E28: Follow-up visits, medicines
B29: Baby's first pediatrician visits (first month) | C29: 3000 | D29: 1,500 – 5,000 | E29: 2-3 visits in first month
B30: Baby essentials — initial setup | C30: 25000 | D30: 10,000 – 60,000 | E30: Crib, car seat, stroller, clothes, bottles
B32: TOTAL BIRTH & PREGNANCY COST | C32: =SUM(C6:C31) -> 317500
B33: Note: Insurance may cover some hospital costs. Check your corporate/personal health policy for maternity coverage.

Sheet First 3 Years
B2: FIRST 3 YEARS — THE SUBSCRIPTION PHASE
B3: These are MONTHLY recurring costs. The first 3 years are expensive because every small bill repeats.
B5: Monthly Expense | C5: Your Estimate (₹/month) | D5: Typical Range | E5: Notes
B6: FEEDING
B7: Baby formula / supplementary food | C7: 3000 | D7: 1,500 – 6,000 | E7: Breastfeeding reduces this significantly
B8: Baby cereal, purees, snacks (6+ months) | C8: 2000 | D8: 1,000 – 4,000 | E8: Homemade vs store-bought matters
B10: DIAPERS & HYGIENE
B11: Diapers (5-6/day average) | C11: 3000 | D11: 2,000 – 5,000 | E11: ~₹35,000-70,000 over 2.5 years
B12: Wipes, rash cream, baby soap, oil | C12: 1500 | D12: 800 – 3,000 | E12: Monthly consumables
B14: HEALTHCARE
B15: Pediatrician visits (1-2/month) | C15: 2000 | D15: 1,000 – 4,000 | E15: Regular checkups + sick visits
B16: Vaccines (private — monthly average) | C16: 1500 | D16: 500 – 3,000 | E16: IAP schedule: ₹20,000-50,000 total over 2 yrs
B17: Medicines (fever, cough, stomach) | C17: 1000 | D17: 500 – 2,000 | E17: Common illnesses are frequent
B19: CHILDCARE
B20: Daycare / creche | C20: 8000 | D20: 5,000 – 20,000 | E20: Metro daycare: ₹8K-20K/month
B21: Nanny / domestic help (baby-dedicated) | C21: 10000 | D21: 5,000 – 18,000 | E21: Full-time nanny in metros: ₹10K-18K
B23: CLOTHING & ESSENTIALS
B24: Baby clothes (they outgrow fast) | C24: 2000 | D24: 1,000 – 4,000 | E24: New sizes every 2-3 months
B25: Toys, books, learning aids | C25: 1000 | D25: 500 – 3,000 | E25: Stimulation matters for development
B26: Baby gear maintenance / replacement | C26: 500 | D26: 200 – 1,500 | E26: Stroller repairs, new bottles, etc.
B29: TOTAL MONTHLY COST (First 3 Years) | C29: =SUM(C6:C28) -> 35500
B30: TOTAL ANNUAL COST | C30: =C29*12 -> 426000
B31: TOTAL COST FOR 3 YEARS | C31: =C29*36 -> 1278000

Sheet Education 3-18
B2: EDUCATION COST — AGE 3 TO 18
B3: Source: CMS Education 2025 — Avg per student: ₹2,863 (govt) / ₹25,002 (non-govt). Course fees alone: ₹7,111 avg. Urban: ₹15,143.
B5: Education Stage | C5: Govt School (₹/yr) | D5: Pvt Mid-Range (₹/yr) | E5: Pvt Premium (₹/yr) | F5: Source / Notes
B6: ANNUAL SCHOOL FEES
B7: Pre-Primary (Age 3-5) — Nursery/KG | C7: 3000 | D7: 50000 | E7: 150000 | F7: 2 years — playschool + KG
B8: Primary (Class 1-5) | C8: 5000 | D8: 80000 | E8: 200000 | F8: CMS 2025: govt avg ₹2,863/yr
B9: Middle School (Class 6-8) | C9: 6000 | D9: 100000 | E9: 250000 | F9: Fees rise with class level
B10: Secondary (Class 9-10) | C10: 8000 | D10: 120000 | E10: 300000 | F10: Board exam year — extra pressure
B11: Higher Secondary (Class 11-12) | C11: 10000 | D11: 140000 | E11: 350000 | F11: Stream choice adds cost (Science > Arts)
B13: ANNUAL ADD-ON COSTS (per year)
B14: Books & Stationery | C14: 2000 | D14: 5000 | E14: 10000 | F14: CMS 2025 avg: ₹2,002
B15: Uniform (2 sets/year) | C15: 2000 | D15: 5000 | E15: 8000 | F15: Branded uniforms cost more
B16: School Transport | C16: 0 | D16: 20000 | E16: 36000 | F16: CMS 2025 avg: ₹1,842. School bus/van
B17: Activities & Sports Fees | C17: 0 | D17: 15000 | E17: 30000 | F17: Swimming, music, art, robotics
B18: School Trips & Events | C18: 500 | D18: 5000 | E18: 15000 | F18: Excursions, annual day, sports day
B19: Devices — Tablet/Laptop (amortized) | C19: 0 | D19: 5000 | E19: 10000 | F19: One device every 3-4 years
B20: Projects, Competitions, Exams | C20: 500 | D20: 4000 | E20: 8000 | F20: Science fairs, olympiads, registration
B22: TOTAL EDUCATION COST CALCULATOR (15 years: age 3 to 18)
B23: Choose your school type → | C23: Govt School | D23: Pvt Mid-Range | E23: Pvt Premium
B24: Pre-Primary — 2 years | C24: =(C7+SUM(C$14:C$20))*2 -> 16000 | D24: =(D7+SUM(D$14:D$20))*2 -> 218000 | E24: =(E7+SUM(E$14:E$20))*2 -> 534000
B25: Primary — 5 years | C25: =(C8+SUM(C$14:C$20))*5 -> 50000 | D25: =(D8+SUM(D$14:D$20))*5 -> 695000 | E25: =(E8+SUM(E$14:E$20))*5 -> 1585000
B26: Middle School — 3 years | C26: =(C9+SUM(C$14:C$20))*3 -> 33000 | D26: =(D9+SUM(D$14:D$20))*3 -> 477000 | E26: =(E9+SUM(E$14:E$20))*3 -> 1101000
B27: Secondary — 2 years | C27: =(C10+SUM(C$14:C$20))*2 -> 26000 | D27: =(D10+SUM(D$14:D$20))*2 -> 358000 | E27: =(E10+SUM(E$14:E$20))*2 -> 834000
B28: Higher Secondary — 2 years | C28: =(C11+SUM(C$14:C$20))*2 -> 30000 | D28: =(D11+SUM(D$14:D$20))*2 -> 398000 | E28: =(E11+SUM(E$14:E$20))*2 -> 934000
B29: One-time Admission / Registration Fees | C29: 5000 | D29: 50000 | E29: 200000
B31: TOTAL EDUCATION (3 to 18) — NO INFLATION | C31: =SUM(C24:C29) -> 160000 | D31: =SUM(D24:D29) -> 2196000 | E31: =SUM(E24:E29) -> 5188000
B33: WARNING: These are TODAY's prices. With 10% education inflation, costs can DOUBLE in 7-8 years. See the Total Summary sheet for inflation-adjusted numbers.

Sheet Coaching & Tuition
B2: COACHING & TUITION — THE SECOND SCHOOL
B3: Source: CMS 2025 — 27% of all students take private coaching. Urban: 30.7%. Cost rises sharply with class level.
B5: Stage | C5: Annual Cost (₹) | D5: Years | E5: Notes
B6: Secondary (Class 9-10) — Board prep | C6: 48000 | D6: 2 | E6: CMS avg: ₹4,183/yr. Board coaching: ₹3K-5K/month
B7: Higher Sec (11-12) — Stream coaching | C7: 72000 | D7: 2 | E7: CMS avg: ₹6,384/yr. Science stream: ₹5K-8K/month
B8: Competitive Exam Prep (JEE/NEET/CLAT) | C8: 150000 | D8: 2 | E8: Kota-style coaching: ₹1-2.5L/year
B9: Hobby/Skill Classes (coding, music, sports) | C9: 40000 | D9: 10 | E9: ₹2,000/month average across years
B11: TOTAL COACHING COST (No Inflation) | C11: =SUMPRODUCT(C6:C9,D6:D9) -> 940000
B13: Earlier, parents paid for school. Now many parents pay for school AND then pay again because school doesn't feel enough.

Sheet Healthcare 0-18
B2: HEALTHCARE COST — BIRTH TO 18
B4: Healthcare Item | C4: Total Estimated Cost (₹) | D4: Notes
B5: VACCINATIONS (0-5 years)
B6: Government UIP vaccines (free) | C6: 0 | D6: BCG, OPV, Pentavalent, MR — free at govt centres
B7: Private vaccination (IAP full schedule) | C7: 40000 | D7: ₹20,000-50,000 total. Painless options cost more
B8: Optional vaccines (Varicella, Hep A, HPV) | C8: 15000 | D8: Not in UIP but recommended by pediatricians
B10: REGULAR HEALTHCARE (0-18 years)
B11: Pediatrician visits — year 1 (12 visits) | C11: 18000 | D11: ₹1,000-2,500 per visit
B12: Pediatrician visits — year 2-5 (6/year × 4 yrs) | C12: 36000 | D12: Reducing frequency as child grows
B13: Doctor visits — age 6-18 (3/year × 13 yrs) | C13: 58500 | D13: ₹1,500/visit average
B14: Medicines & OTC supplies (18 years) | C14: 108000 | D14: ~₹500/month average over 18 years
B15: Dental care (age 5-18) | C15: 50000 | D15: Braces alone: ₹30,000-80,000
B16: Eye care / spectacles | C16: 20000 | D16: Screen time = early specs for many kids
B18: INSURANCE & EMERGENCY
B19: Health insurance premium — child add-on (18 yrs) | C19: 180000 | D19: ~₹10,000/year additional premium
B20: Emergency medical fund (contingency) | C20: 100000 | D20: NICU, accidents, surgeries — hope you don't need it
B21: Hospitalization (1-2 episodes in 18 yrs) | C21: 50000 | D21: Dengue, fractures, infections — common
B23: TOTAL HEALTHCARE COST (0-18 years) | C23: =SUM(C6:C22) -> 675500

Sheet TOTAL SUMMARY
B2: TOTAL COST OF RAISING A CHILD IN INDIA
B3: This pulls from all other sheets. Column C = Today's prices. Column D = With inflation (rough estimate).
B5: Cost Bucket | C5: At Today's Prices (₹) | D5: Inflation-Adjusted Estimate (₹) | E5: Assumptions
B6: 1. BIRTH & PREGNANCY | C6: ='Birth Cost'!C32 -> 317500 | D6: =C6*1 -> 317500 | E6: One-time cost — no inflation needed
B7: 2. FIRST 3 YEARS (0-3) | C7: ='First 3 Years'!C31 -> 1278000 | D7: =C7*1.18 -> 1508040 | E7: 3 years of 6% avg inflation
B8: 3. EDUCATION — Govt School (15 yrs) | C8: ='Education 3-18'!C31 -> 160000 | D8: =C8*2.16 -> 345600 | E8: 15 yrs × 10% education inflation (compounded ~2.16x)
B9: 4. EDUCATION — Pvt Mid-Range (15 yrs) | C9: ='Education 3-18'!D31 -> 2196000 | D9: =C9*2.16 -> 4743360 | E9: Same inflation multiplier
B10: 5. EDUCATION — Pvt Premium (15 yrs) | C10: ='Education 3-18'!E31 -> 5188000 | D10: =C10*2.16 -> 11206080 | E10: Same inflation multiplier
B11: 6. COACHING & TUITION | C11: ='Coaching & Tuition'!C11 -> 940000 | D11: =C11*1.8 -> 1692000 | E11: ~10 years avg, 8% inflation
B12: 7. HEALTHCARE (0-18 years) | C12: ='Healthcare 0-18'!C23 -> 675500 | D12: =C12*1.6 -> 1080800 | E12: 18 yrs × 8% health inflation (spread)
B13: 8 EMERGENCY BUFFER | C13: =sum(C6:C12)*10% -> 1075500 | D13: =C13*1.6 -> 1720800 | E13: 18 yrs × 8% health inflation (spread)
B14: GRAND TOTAL — GOVERNMENT SCHOOL PATH
B15: Total (Birth + 3 Yrs + Govt School + Coaching + Health + Buffer) | C15: =C6+C7+C8+C11+C12+C13 -> 4446500 | D15: =D6+D7+D8+D11+D12+D13 -> 6664740
B17: GRAND TOTAL — PRIVATE MID-RANGE SCHOOL PATH
B18: Total (Birth + 3 Yrs + Pvt Mid + Coaching + Health + Buffer) | C18: =C6+C7+C9+C11+C12+C13 -> 6482500 | D18: =D6+D7+D9+D11+D12+D13 -> 11062500
B20: GRAND TOTAL — PRIVATE PREMIUM SCHOOL PATH
B21: Total (Birth + 3 Yrs + Pvt Premium + Coaching + Health + Buffer) | C21: =C6+C7+C10+C11+C12+C13 -> 9474500 | D21: =D6+D7+D10+D11+D12+D13 -> 17525220
B24: THE BABY DECISION FRAMEWORK
B25: Question 1: Do we want a child, or do we want to satisfy family expectations?
B26: Question 2: Are we delaying because of fear, or because our system is genuinely not ready?
B27: Question 3: If we have a child, whose life changes the most?
B29: Plan these 5 systems BEFORE having a child:
B30: ✓ Care System — Who takes care of the child?
B31: ✓ Money System — Can we afford it without stress?
B32: ✓ Career System — Whose career adjusts, and how?
B33: ✓ Emergency System — What if something goes wrong?
B34: ✓ Support System — Family, friends, or paid help?
B36: "Having a child is not a bad financial decision. But pretending that love alone will handle the cost is dangerous."
